{
  "version": "2026061914",
  "hash": "5ca30e49b5f5",
  "rules_count": 9659,
  "updated_at": "2026-06-19T14:30:00.313905+00:00",
  "expires_hours": 24,
  "stats": {
    "ads": {
      "total_latest": 56859,
      "delta_new": 8430
    },
    "privacy": {
      "total_latest": 55376,
      "delta_new": 760
    },
    "cookie": {
      "total_latest": 2089,
      "delta_new": 176
    },
    "annoyance": {
      "total_latest": 4113,
      "delta_new": 276
    },
    "social": {
      "total_latest": 664,
      "delta_new": 17
    }
  },
  "delta_url": "https://uShieldApp.github.io/uShield/rules/v1.0.0/delta_rules.json",
  "outdated_baseline": false
}