{
  "version": "2026071210",
  "hash": "ded5daa372c9",
  "rules_count": 1479,
  "updated_at": "2026-07-12T10:13:24.298964+00:00",
  "expires_hours": 24,
  "stats": {
    "ads": {
      "total_latest": 55166,
      "delta_new": 1450
    },
    "privacy": {
      "total_latest": 55494,
      "delta_new": 25
    },
    "cookie": {
      "total_latest": 2089,
      "delta_new": 2
    },
    "annoyance": {
      "total_latest": 4119,
      "delta_new": 2
    },
    "social": {
      "total_latest": 664,
      "delta_new": 0
    }
  },
  "delta_url": "https://uShieldApp.github.io/uShield/rules/v1.0.7/delta_rules.json",
  "outdated_baseline": false
}